[
  {
    "id": 1,
    "title": "Legend of Zelda",
    "description": "hi",
    "developer": "Ninendo",
    "platform": "Nintendo Entertainment System",
    "release_date": "1986-02-21",
    "genre": "Action-adventure"
  },
  {
    "id": 2,
    "title": "Pokemon",
    "description": "Gotta catch them all!............",
    "developer": "Game Freak",
    "platform": "",
    "genre": "Role-playing"
  },
  {
    "id": 3,
    "title": "Mario",
    "description": "Save Princess Peach??",
    "developer": "Nintendo EAD",
    "platform": ".......",
    "genre": "Platform"
  },
  {
    "id": 4,
    "title": "Darksoul",
    "description": "just die a lot!!.......",
    "developer": "FromSoftware",
    "platform": "PlayStation 3",
    "release_date": "2018-05-24", 
    "genre": "Action role-playing"
  }
]